ansible_sign/__init__.py
ansible_sign/_version.py
ansible_sign/cli.py
ansible_sign/version.py
ansible_sign/checksum/__init__.py
ansible_sign/checksum/base.py
ansible_sign/checksum/differ/__init__.py
ansible_sign/checksum/differ/base.py
ansible_sign/checksum/differ/distlib_manifest.py
ansible_sign/signing/__init__.py
ansible_sign/signing/base.py
ansible_sign/signing/gpg/__init__.py
ansible_sign/signing/gpg/signer.py
ansible_sign/signing/gpg/verifier.py
ansible_sign-0.1.2.dist-info/licenses/AUTHORS.rst
ansible_sign-0.1.2.dist-info/licenses/LICENSE.txt
ansible_sign-0.1.2.dist-info/METADATA
ansible_sign-0.1.2.dist-info/WHEEL
ansible_sign-0.1.2.dist-info/entry_points.txt
ansible_sign-0.1.2.dist-info/top_level.txt
ansible_sign-0.1.2.dist-info/RECORD
