Metadata-Version: 2.4
Name: ansible-sign
Version: 0.1.2
Summary: Ansible content validation library and CLI
Author-email: Rick Elrod <relrod@redhat.com>
License-Expression: MIT
Project-URL: changelog, https://github.com/ansible/ansible-sign/releases
Project-URL: documentation, https://ansible.readthedocs.io/projects/sign/
Project-URL: homepage, https://github.com/ansible/ansible-sign
Project-URL: repository, https://github.com/ansible/ansible-sign
Keywords: ansible,sign
Classifier: Development Status :: 5 - Production/Stable
Classifier: Environment :: Console
Classifier: Intended Audience :: Developers
Classifier: Intended Audience :: Information Technology
Classifier: Intended Audience :: System Administrators
Classifier: Operating System :: MacOS
Classifier: Operating System :: POSIX
Classifier: Programming Language :: Python :: 3
Classifier: Programming Language :: Python :: 3.10
Classifier: Programming Language :: Python :: 3.11
Classifier: Programming Language :: Python :: 3.12
Classifier: Programming Language :: Python :: 3.13
Classifier: Programming Language :: Python :: 3.14
Classifier: Programming Language :: Python :: 3 :: Only
Classifier: Programming Language :: Python
Classifier: Topic :: System :: Systems Administration
Classifier: Topic :: Software Development :: Quality Assurance
Classifier: Topic :: Software Development :: Testing
Classifier: Topic :: Utilities
Requires-Python: >=3.9
License-File: LICENSE.txt
License-File: AUTHORS.rst
Requires-Dist: distlib
Requires-Dist: python-gnupg
Provides-Extra: docs
Requires-Dist: sphinx-ansible-theme>=0.10.1; extra == "docs"
Requires-Dist: sphinx>=3.2.1; extra == "docs"
Provides-Extra: test
Requires-Dist: pytest; extra == "test"
Requires-Dist: pytest-cov; extra == "test"
Requires-Dist: setuptools; extra == "test"
Dynamic: license-file
